easy_analysis/__init__.py
easy_analysis/_constants.py
easy_analysis/cluster.py
easy_analysis/core/__init__.py
easy_analysis/core/_errors.py
easy_analysis/data/__init__.py
easy_analysis/data/outliers.py
easy_analysis/data/summary.py
easy_analysis/plots/__init__.py
easy_analysis/plots/insights.py
easy_analysis/plots/multivariate.py
easy_analysis/plots/univariate.py
arv_easy_analysis-0.1.1.dist-info/LICENSE
arv_easy_analysis-0.1.1.dist-info/METADATA
arv_easy_analysis-0.1.1.dist-info/WHEEL
arv_easy_analysis-0.1.1.dist-info/top_level.txt
arv_easy_analysis-0.1.1.dist-info/RECORD
